nunpy/__init__.py
nunpy/rechape.py
skmtpy-0.3.1.dist-info/METADATA
skmtpy-0.3.1.dist-info/WHEEL
skmtpy-0.3.1.dist-info/top_level.txt
skmtpy-0.3.1.dist-info/RECORD
